cambridge/__init__.py
cambridge/args.py
cambridge/const.py
cambridge/define.py
cambridge/dictionary.py
cambridge/element.py
cambridge/utils.py
cambridge_cli-1.2.dist-info/METADATA
cambridge_cli-1.2.dist-info/WHEEL
cambridge_cli-1.2.dist-info/entry_points.txt
cambridge_cli-1.2.dist-info/top_level.txt
cambridge_cli-1.2.dist-info/RECORD
